setup.py
april3rd/LONG
april3rd/VERSION
april3rd/__init__.py
april3rd/family.py
april3rd/loader.py
april3rd/relationship.py
april3rd/secret.py
april3rd/tmp.py
april3rd/utils.py
april3rd.egg-info/PKG-INFO
april3rd.egg-info/SOURCES.txt
april3rd.egg-info/dependency_links.txt
april3rd.egg-info/requires.txt
april3rd.egg-info/top_level.txt
april3rd.egg-info/zip-safe
april3rd/birthday/__init__.py
april3rd/birthday/lunar.py
april3rd/birthday/show.py
april3rd/experience/__init__.py
april3rd/experience/show.py
april3rd/experience/utils.py
april3rd/memories/__init__.py
april3rd/memories/__init__.pyc
april3rd/memories/cache_birthday.pkl
april3rd/memories/keep.pkl
april3rd/memories/time_machine.pkl