Metadata-Version: 1.1
Name: april3rd
Version: 0.5.20.4
Summary: 喝药和乖乖的6个月纪念日
Home-page: https://github.com/Syhen/april3rd
Author: heyao
Author-email: syhens@163.com
License: UNKNOWN
Platform: UNKNOWN
Classifier: Development Status :: 4 - Beta
Classifier: Programming Language :: Python :: 3.6
